Metadata-Version: 1.1
Name: plotmygsheet
Version: 0.0.1
Summary: This package will plot a graph between the two columns of your choice from google sheet.
Home-page: UNKNOWN
Author: Suraj Patidar
Author-email: surjpatidar9999@gmail.com
License: MIT
Keywords: plotspreadsheet
Platform: UNKNOWN
Classifier: Development Status :: 5 - Production/Stable
Classifier: Intended Audience :: Education
Classifier: Operating System :: Microsoft :: Windows :: Windows 10
Classifier: License :: OSI Approved :: MIT License
Classifier: Programming Language :: Python :: 3
